chatware/__init__.py
riverbank/__init__.py
chatware-0.0.1.dist-info/LICENSE.txt
chatware-0.0.1.dist-info/METADATA
chatware-0.0.1.dist-info/WHEEL
chatware-0.0.1.dist-info/top_level.txt
chatware-0.0.1.dist-info/RECORD
