Metadata-Version: 2.1
Name: chatware
Version: 0.0.1
Summary: An utility in python
Home-page: https://github.com/acegik/chatware
Author: acegik
License: GPL-3.0
Download-URL: https://github.com/acegik/chatware/downloads
Keywords: utility
Platform: UNKNOWN
Requires-Python: >=2.7,!=3.0.*,!=3.1.*,!=3.2.*,!=3.3.*
